{
    "intro_images": [
        {
            "path": "bg-1.jpg",
            "color": "rgb(138, 198, 221)"
        },
        {
            "path": "bg-2.jpg",
            "color": "rgb(143, 158, 185)"
        },
        {
            "path": "bg-3.jpg",
            "color": "rgb(203, 99, 61)"
        },
        {
            "path": "bg-4.jpg",
            "color": "rgb(227, 171, 112)"
        }
    ],
    "quote": {
        "content": "To err is human. To really foul things up, you need a computer!",
        "author": "Paul R. Ehrlich"
    },
    "footer": {
        "text": "Copyright \u00a9 2023 Xuan (Tom) Zhao All Rights Reserved. <br /> Created by Xuan (Tom) Zhao"
    },
    "social_media": [
        {
            "icon": "fab, facebook",
            "link": "https://www.facebook.com/xuan.zhao.14019",
            "name": "Facebook"
          },
          {
            "icon": "fab, instagram",
            "link": "https://www.instagram.com/tomzhao1999",
            "name": "Instagram"
          },
          {
            "icon": "fab, github",
            "link": "https://www.github.com/zhao-xuan",
            "name": "Github"
          },
          {
            "icon": "fab, linkedin",
            "link": "https://www.linkedin.com/in/zhaoxuan0914/",
            "name": "LinkedIn"
          },
          {
            "icon": "fab, weixin",
            "link": "javascript:alert('Removed due to spamming!');",
            "name": "WeChat"
          },
          {
            "icon": "fab, telegram",
            "link": "javascript:alert('Removed due to spamming!');",
            "name": "Telegram"
          },
          {
            "icon": "fab, whatsapp",
            "link": "javascript:alert('Removed due to spamming!');",
            "name": "Whatsapp"
          }
    ]
}